babysteps/__init__.py
tutorial/__init__.py
babysteps-0.0.1.dist-info/LICENSE.txt
babysteps-0.0.1.dist-info/METADATA
babysteps-0.0.1.dist-info/WHEEL
babysteps-0.0.1.dist-info/top_level.txt
babysteps-0.0.1.dist-info/RECORD
