Metadata-Version: 2.1
Name: babysteps
Version: 0.0.1
Summary: Python library for building interactive programming babystepss.
Home-page: https://github.com/gadgetoid/babysteps-python
Author: Philip Howard
Author-email: phil@gadgetoid.com
License: MIT
Project-URL: GitHub, https://www.github.com/gadgetoid/babysteps-python
Keywords: Raspberry Pi
Platform: UNKNOWN
Classifier: Development Status :: 4 - Beta
Classifier: Operating System :: POSIX :: Linux
Classifier: License :: OSI Approved :: MIT License
Classifier: Intended Audience :: Developers
Classifier: Programming Language :: Python :: 3
Classifier: Topic :: Software Development
Classifier: Topic :: Software Development :: Libraries
Classifier: Topic :: System :: Hardware
Requires-Python: >= 3.5
